linkml_owl/__init__.py
linkml_owl/crossproducts/__init__.py
linkml_owl/crossproducts/cross_product_generator.py
linkml_owl/dumpers/__init__.py
linkml_owl/dumpers/owl_dumper.py
linkml_owl/util/__init__.py
linkml_owl/util/csv_converter.py
linkml_owl/util/loader_wrapper.py
linkml_owl/util/trim_yaml.py
linkml_owl-0.4.2.dist-info/METADATA
linkml_owl-0.4.2.dist-info/WHEEL
linkml_owl-0.4.2.dist-info/entry_points.txt
linkml_owl-0.4.2.dist-info/RECORD
