Metadata-Version: 2.1
Name: linkml_owl
Version: 0.4.2
Summary: OWL mappings for Linked Open Data Modeling Language
Home-page: https://github.com/linkml/linkml-owl
Keywords: linkml,owl
Author: Chris Mungall
Author-email: cjmungall@lbl.gov
Requires-Python: >=3.8.1,<4.0.0
Classifier: Development Status :: 4 - Beta
Classifier: Environment :: Console
Classifier: Intended Audience :: Developers
Classifier: Intended Audience :: Healthcare Industry
Classifier: Intended Audience :: Science/Research
Classifier: License :: CC0 1.0 Universal (CC0 1.0) Public Domain Dedication
Classifier: Programming Language :: Python :: 3
Classifier: Programming Language :: Python :: 3.9
Classifier: Programming Language :: Python :: 3.10
Classifier: Programming Language :: Python :: 3.11
Classifier: Programming Language :: Python :: 3.12
Classifier: Programming Language :: Python :: 3 :: Only
Classifier: Programming Language :: Python :: 3.7
Classifier: Programming Language :: Python :: 3.8
Requires-Dist: Jinja2 (>=3.0.3)
Requires-Dist: click
Requires-Dist: funowl (>=0.2.3)
Requires-Dist: linkml (>=1.7.10,<2.0.0)
Requires-Dist: linkml-runtime (>=1.7.0)
Project-URL: Documentation, https://github.com/linkml/linkml-owl
Project-URL: Repository, https://github.com/linkml/linkml-owl
